drf_payload_customizer/__init__.py
drf_payload_customizer/mixins/__init__.py
drf_payload_customizer/mixins/payload_converter_mixin.py
drf_payload_customizer/mixins/payload_no_null_or_none_mixin.py
drf_payload_customizer/mixins/payload_transformation_mixin.py
drf_payload_customizer/mixins/payload_translation_mixin.py
drf_payload_customizer-0.1.1.dist-info/LICENSE
drf_payload_customizer-0.1.1.dist-info/METADATA
drf_payload_customizer-0.1.1.dist-info/WHEEL
drf_payload_customizer-0.1.1.dist-info/top_level.txt
drf_payload_customizer-0.1.1.dist-info/RECORD
