Metadata-Version: 2.1
Name: drf-payload-customizer
Version: 0.1.1
Summary: This package allows you to customize your django-rest-framework serializer i/o to make modern frontend frameworks happy.
Home-page: https://github.com/3YOURMIND/drf-payload-customizer
Author: 3YOURMIND
Author-email: 01tonythomas@gmail.com
License: Apache License 2.0
Keywords: django drf rest converter mapping case transformation
License-File: LICENSE
